ejpiaj-0.3.2.dist-info/WHEEL
ejpiaj-0.3.2.dist-info/top_level.txt
ejpiaj-0.3.2.dist-info/RECORD
ejpiaj-0.3.2.dist-info/DESCRIPTION.rst
ejpiaj-0.3.2.dist-info/pydist.json
ejpiaj-0.3.2.dist-info/METADATA
ejpiaj/runner.py
ejpiaj/ejpiaj-cli
ejpiaj/__init__.py
ejpiaj/registry.py
ejpiaj/assertions.py
ejpiaj/core.py
ejpiaj/decorators.py
ejpiaj/variable_extractor.py
ejpiaj/parsers.py
ejpiaj-0.3.2.data/scripts/ejpiaj-cli
