Metadata-Version: 2.0
Name: ejpiaj
Version: 0.3.2
Summary: ejpiaj
Home-page: https://github.com/onjin/ejpiaj
Author: Marek Wywiał
Author-email: onjinx@gmail.com
License: BSD
Keywords: ejpiaj
Platform: UNKNOWN
Classifier: Development Status :: 2 - Pre-Alpha
Classifier: Intended Audience :: Developers
Classifier: License :: OSI Approved :: BSD License
Classifier: Natural Language :: English
Classifier: Programming Language :: Python :: 2
Classifier: Programming Language :: Python :: 2.6
Classifier: Programming Language :: Python :: 2.7
Classifier: Programming Language :: Python :: 3
Classifier: Programming Language :: Python :: 3.3
Requires-Dist: requests
Requires-Dist: simplejson
Requires-Dist: clint
Requires-Dist: baker
Requires-Dist: pyyaml
